{
    "userId": 38990540,
    "authorName": "bungotakadasword",
    "from": "&quot;bungotakadasword&quot; &lt;MuramasaIII@...&gt;",
    "profile": "bungotakadasword",
    "replyTo": "LIST",
    "senderId": "zbxwyQczhEThHmBHTDfoVFDOwGqpt3morfh8IPm3fnyjzSUoXYmQ6GGj9Y4F_TgdoSSETEwk4ftWhuUpEvRqAeMsAz5O6Gc1YEeY7wNdEA",
    "spamInfo": {
        "isSpam": false,
        "reason": "0"
    },
    "subject": "Re: shinsa question",
    "postDate": "1074568617",
    "msgId": 1543,
    "canDelete": false,
    "contentTrasformed": false,
    "systemMessage": false,
    "headers": {
        "messageIdInHeader": "PGJ1aTZqOSs5YmhsQGVHcm91cHMuY29tPg==",
        "inReplyToHeader": "PHhvOHZmbjdzMnFvLmZzZkBmZWFyLnhoYXNjLmNvbT4="
    },
    "prevInTopic": 1542,
    "nextInTopic": 1544,
    "prevInTime": 1542,
    "nextInTime": 1544,
    "topicId": 1515,
    "numMessagesInTopic": 34,
    "msgSnippet": "... not always true......... case in point, if they belong to the Ii clan, they are expected to wear red. -M",
    "rawEmail": "Return-Path: &lt;MuramasaIII@...&gt;\r\nX-Sender: MuramasaIII@...\r\nX-Apparently-To: nihontostudy@yahoogroups.com\r\nReceived: (qmail 60732 invoked from network); 20 Jan 2004 03:17:01 -0000\r\nReceived: from unknown (66.218.66.172)\n  by m2.grp.scd.yahoo.com with QMQP; 20 Jan 2004 03:17:01 -0000\r\nReceived: from unknown (HELO n38.grp.scd.yahoo.com) (66.218.66.106)\n  by mta4.grp.scd.yahoo.com with SMTP; 20 Jan 2004 03:17:01 -0000\r\nReceived: from [66.218.67.157] by n38.grp.scd.yahoo.com with NNFMP; 20 Jan 2004 03:16:57 -0000\r\nDate: Tue, 20 Jan 2004 03:16:57 -0000\r\nTo: nihontostudy@yahoogroups.com\r\nMessage-ID: &lt;bui6j9+9bhl@...&gt;\r\nIn-Reply-To: &lt;xo8vfn7s2qo.fsf@...&gt;\r\nUser-Agent: eGroups-EW/0.82\r\nMIME-Version: 1.0\r\nContent-Type: text/plain; charset=ISO-8859-1\r\nContent-Length: 221\r\nX-Mailer: Yahoo Groups Message Poster\r\nX-eGroups-Remote-IP: 66.218.66.106\r\nFrom: &quot;bungotakadasword&quot; &lt;MuramasaIII@...&gt;\r\nSubject: Re: shinsa question\r\nX-Yahoo-Group-Post: member; u=38990540\r\nX-Yahoo-Profile: bungotakadasword\r\n\r\n&gt; I understand that red saya were banned on low ranking samurai, along\n&gt; with other red articles of clothing\n\n\n\nnot always true.........\ncase in point, if they belong to the Ii clan, they are expected to \nwear red.\n\n\n\n-M\n\n\n"
}