{
    "userId": 122856650,
    "authorName": "Richard Turner",
    "from": "Richard Turner &lt;ikkanshi@...&gt;",
    "profile": "retalt",
    "replyTo": "LIST",
    "senderId": "IC6t9uKZT7IEPM2Qb1DSN97nWQO5jqqxbcnxLFquYAUiBRuVinPVpIcsSBNQ5tWXThToqlLh4Po8CTp27txAg6Kv3kAgXZqPsxIIWr_Qxw",
    "spamInfo": {
        "isSpam": false,
        "reason": "0"
    },
    "subject": "Crass Commercial Message - Books for Sale",
    "postDate": "1102252594",
    "msgId": 2438,
    "canDelete": false,
    "contentTrasformed": false,
    "systemMessage": false,
    "headers": {
        "messageIdInHeader": "PDQxQjMwQTMyLjIwMjA5MDhAd2VzdG5ldC5jb20uYXU+"
    },
    "prevInTopic": 0,
    "nextInTopic": 0,
    "prevInTime": 2437,
    "nextInTime": 2439,
    "topicId": 2438,
    "numMessagesInTopic": 1,
    "msgSnippet": "All, I have listed several books for sale on Ebay. If anyone is interested, please take a look. Don t bother with the game unless you are really board :-) ",
    "rawEmail": "Return-Path: &lt;ikkanshi@...&gt;\r\nX-Sender: ikkanshi@...\r\nX-Apparently-To: nihontostudy@yahoogroups.com\r\nReceived: (qmail 23717 invoked from network); 5 Dec 2004 13:14:05 -0000\r\nReceived: from unknown (66.218.66.218)\n  by m24.grp.scd.yahoo.com with QMQP; 5 Dec 2004 13:14:05 -0000\r\nReceived: from unknown (HELO vscan01.westnet.com.au) (203.10.1.131)\n  by mta3.grp.scd.yahoo.com with SMTP; 5 Dec 2004 13:14:05 -0000\r\nReceived: from localhost (localhost.localdomain [127.0.0.1])\n\tby localhost (Postfix) with ESMTP id 1A0C65F2AC\n\tfor &lt;nihontostudy@yahoogroups.com&gt;; Sun,  5 Dec 2004 21:13:33 +0800 (WST)\r\nReceived: from vscan01.westnet.com.au ([127.0.0.1])\n by localhost (vscan01.westnet.com.au [127.0.0.1]) (amavisd-new, port 10024)\n with ESMTP id 28872-16 for &lt;nihontostudy@yahoogroups.com&gt;;\n Sun,  5 Dec 2004 21:13:33 +0800 (WST)\r\nReceived: from [192.168.0.7] (dsl-202-72-174-81.wa.westnet.com.au [202.72.174.81])\n\tby vscan01.westnet.com.au (Postfix) with ESMTP id C7A7957907\n\tfor &lt;nihontostudy@yahoogroups.com&gt;; Sun,  5 Dec 2004 21:13:32 +0800 (WST)\r\nMessage-ID: &lt;41B30A32.2020908@...&gt;\r\nDate: Sun, 05 Dec 2004 21:16:34 +0800\r\nUser-Agent: Mozilla/5.0 (Windows; U; Windows NT 5.0; en-US; rv:1.7.2) Gecko/20040804 Netscape/7.2 (ax)\r\nX-Accept-Language: en-us, en, ja\r\nMIME-Version: 1.0\r\nTo: &quot;nihontostudy@yahoogroups.com&quot; &lt;nihontostudy@yahoogroups.com&gt;\r\nX-eGroups-Remote-IP: 203.10.1.131\r\nFrom: Richard Turner &lt;ikkanshi@...&gt;\r\nReply-To: ikkanshi@...\r\nSubject: Crass Commercial Message - Books for Sale\r\nX-Yahoo-Group-Post: member; u=122856650\r\nX-Yahoo-Profile: retalt\r\nContent-Type: text/plain; charset=US-ASCII\r\nContent-Transfer-Encoding: 7bit\r\n\r\nAll, I have listed several books for sale on Ebay. If anyone is \ninterested, please take a look. Don&#39;t bother with the game unless you \nare really board :-)\n\nCheers\n\nRich\n\nhttp://tinyurl.com/5ghqe\n\n\n\n[Non-text portions of this message have been removed]\n\n\n"
}