{
    "userId": 123364401,
    "authorName": "nihontochicken",
    "from": "&quot;nihontochicken&quot; &lt;rick@...&gt;",
    "profile": "nihontochicken",
    "replyTo": "LIST",
    "senderId": "XsK6Lss33ckkyFkWEjn1tKFbnwlcVY9G89woMKHJmJKvBVdOd8UwfGrFbtoYYsxQZeej-h0ULCP8ij-oJ4OFZaG3nydKUs1uO-3R",
    "spamInfo": {
        "isSpam": false,
        "reason": "0"
    },
    "subject": "Re: Musashi&#39;s sword",
    "postDate": "1103603175",
    "msgId": 2456,
    "canDelete": false,
    "contentTrasformed": false,
    "systemMessage": false,
    "headers": {
        "messageIdInHeader": "PGNxODhsNytybWJtQGVHcm91cHMuY29tPg==",
        "inReplyToHeader": "PDAwMDcwMWM0ZTcwYyQ0YmE5MGI1MCQzYTAwMTBhY0BreW91aW5udC5zaG93YS5zd3UuYWMuanA+"
    },
    "prevInTopic": 2455,
    "nextInTopic": 2458,
    "prevInTime": 2455,
    "nextInTime": 2457,
    "topicId": 2451,
    "numMessagesInTopic": 11,
    "msgSnippet": "... Okay, well, that explains it.  No wonder all the left-handed compliments for Gordon s Kanabo treasures .  Hahahaha!!! NC  ;o)",
    "rawEmail": "Return-Path: &lt;rick@...&gt;\r\nX-Sender: rick@...\r\nX-Apparently-To: nihontostudy@yahoogroups.com\r\nReceived: (qmail 24754 invoked from network); 21 Dec 2004 04:26:18 -0000\r\nReceived: from unknown (66.218.66.167)\n  by m17.grp.scd.yahoo.com with QMQP; 21 Dec 2004 04:26:18 -0000\r\nReceived: from unknown (HELO n12a.bulk.scd.yahoo.com) (66.94.237.20)\n  by mta6.grp.scd.yahoo.com with SMTP; 21 Dec 2004 04:26:18 -0000\r\nReceived: from [66.218.66.58] by n12.bulk.scd.yahoo.com with NNFMP; 21 Dec 2004 04:26:17 -0000\r\nReceived: from [66.218.66.123] by mailer7.bulk.scd.yahoo.com with NNFMP; 21 Dec 2004 04:26:17 -0000\r\nDate: Tue, 21 Dec 2004 04:26:15 -0000\r\nTo: nihontostudy@yahoogroups.com\r\nMessage-ID: &lt;cq88l7+rmbm@...&gt;\r\nIn-Reply-To: &lt;000701c4e70c$4ba90b50$3a0010ac@...&gt;\r\nUser-Agent: eGroups-EW/0.82\r\nMIME-Version: 1.0\r\nContent-Type: text/plain; charset=ISO-8859-1\r\nContent-Length: 257\r\nX-Mailer: Yahoo Groups Message Poster\r\nX-Yahoo-Newman-Property: groups-compose\r\nX-eGroups-Remote-IP: 66.94.237.20\r\nFrom: &quot;nihontochicken&quot; &lt;rick@...&gt;\r\nSubject: Re: Musashi&#39;s sword\r\nX-Yahoo-Group-Post: member; u=123364401\r\nX-Yahoo-Profile: nihontochicken\r\n\r\n\n--- In nihontostudy@yahoogroups.com, &quot;Gordon Robson&quot; &lt;robsongo@s...&gt;\nwrote:\n&gt; Well, it seems clear - lefties are superior!! \n\nOkay, well, that explains it.  No wonder all the &quot;left-handed\ncompliments&quot; for Gordon&#39;s &quot;Kanabo treasures&quot;.  Hahahaha!!!\n\nNC  ;o)\n\n\n\n\n\n"
}