{
    "userId": 97029769,
    "authorName": "falconer",
    "from": "falconer &lt;falconer@...&gt;",
    "profile": "falconj123",
    "replyTo": "LIST",
    "senderId": "KpozbL9hKGooJt-XuuplcwbQa2q7ZNXk1SDeflxiAhKA9VeC6cspfj3H7xu_CTbkLU_0URBSFVaI5gAuKXj1SX2BgqK-9xg",
    "spamInfo": {
        "isSpam": false,
        "reason": "12"
    },
    "subject": "Re: Anybody in Oz know what kind of sword?",
    "postDate": "1131145651",
    "msgId": 3442,
    "canDelete": false,
    "contentTrasformed": false,
    "systemMessage": false,
    "headers": {
        "messageIdInHeader": "PDQzNkJFOUIzLjIwMEBpaW5ldC5uZXQuYXU+",
        "inReplyToHeader": "PDAwMTUwMWM1ZTE3NiQyOTA5MTllMCRkNDI2ZmVhOUBDTE9ORT4=",
        "referencesHeader": "PDAwMTUwMWM1ZTE3NiQyOTA5MTllMCRkNDI2ZmVhOUBDTE9ORT4="
    },
    "prevInTopic": 3441,
    "nextInTopic": 0,
    "prevInTime": 3441,
    "nextInTime": 3443,
    "topicId": 3440,
    "numMessagesInTopic": 3,
    "msgSnippet": "Police are describing it as a samurai sword, more than likely a replica type regards John",
    "rawEmail": "Return-Path: &lt;falconer@...&gt;\r\nX-Sender: falconer@...\r\nX-Apparently-To: nihontostudy@yahoogroups.com\r\nReceived: (qmail 2736 invoked from network); 4 Nov 2005 23:07:28 -0000\r\nReceived: from unknown (66.218.66.167)\n  by m21.grp.scd.yahoo.com with QMQP; 4 Nov 2005 23:07:28 -0000\r\nReceived: from unknown (HELO ihug-mail.icp-qv1-irony5.iinet.net.au) (203.59.1.199)\n  by mta6.grp.scd.yahoo.com with SMTP; 4 Nov 2005 23:07:28 -0000\r\nReceived: from i154-211.nv.iinet.net.au (HELO [127.0.0.1]) ([203.59.154.211])\n  by ihug-mail.icp-qv1-irony5.iinet.net.au with ESMTP; 05 Nov 2005 07:07:26 +0800\r\nX-BrightmailFiltered: true\r\nX-Brightmail-Tracker: AAAAAA==\r\nMessage-ID: &lt;436BE9B3.200@...&gt;\r\nDate: Sat, 05 Nov 2005 07:07:31 +0800\r\nUser-Agent: Mozilla Thunderbird 1.0.6 (Windows/20050716)\r\nX-Accept-Language: en-us, en\r\nMIME-Version: 1.0\r\nTo: token_kenkyu_kai@...\r\nCc: nihontostudy@yahoogroups.com\r\nReferences: &lt;001501c5e176$290919e0$d426fea9@CLONE&gt;\r\nIn-Reply-To: &lt;001501c5e176$290919e0$d426fea9@CLONE&gt;\r\nContent-Type: text/plain; charset=windows-1252; format=flowed\r\nContent-Transfer-Encoding: 7bit\r\nX-eGroups-Msg-Info: 1:12:0:0\r\nFrom: falconer &lt;falconer@...&gt;\r\nSubject: Re: Anybody in Oz know what kind of sword?\r\nX-Yahoo-Group-Post: member; u=97029769; y=6jQEUHnTxhBximbio1_6hzPiPbM7kpuBiYy7bHmGT_tai27Ysw\r\nX-Yahoo-Profile: falconj123\r\n\r\nPolice are describing it as a samurai sword, more than likely a replica type\nregards\nJohn\n\nDavid Zincavage wrote:\n\n&gt;http://www.news.com.au/story/0,10117,17114699-421,00.html\n&gt;\n&gt;  \n&gt;\n\n\n"
}