{
    "userId": 122856650,
    "authorName": "Richard Turner",
    "from": "Richard Turner &lt;ikkanshi@...&gt;",
    "profile": "retalt",
    "replyTo": "LIST",
    "senderId": "Hhp4onK5ac2jsbFjW0tTWIw4oZjA4QrYcRoky76Vg7GZVIFmPbCMGF1_Z67o_xqU3OKCnirjLb6FSHiPJNDpwWIMcwpowgqJ_wXjxa6Tcw",
    "spamInfo": {
        "isSpam": false,
        "reason": "12"
    },
    "subject": "tsuba question",
    "postDate": "1132732796",
    "msgId": 3506,
    "canDelete": false,
    "contentTrasformed": false,
    "systemMessage": false,
    "headers": {
        "messageIdInHeader": "PDQzODQyMTdDLjIwNjAxMDFAd2VzdG5ldC5jb20uYXU+",
        "inReplyToHeader": "PGRsbHI3citkYmw0QGVHcm91cHMuY29tPg==",
        "referencesHeader": "PGRsbHI3citkYmw0QGVHcm91cHMuY29tPg=="
    },
    "prevInTopic": 3499,
    "nextInTopic": 0,
    "prevInTime": 3505,
    "nextInTime": 3507,
    "topicId": 3499,
    "numMessagesInTopic": 2,
    "msgSnippet": "http://www.nihonto-club.net/upload/joyimages/2440.jpg Hello group, I have a small Ji Sukashi tsuba I think is Edo Owari school. It has long running tokettsu in",
    "rawEmail": "Return-Path: &lt;ikkanshi@...&gt;\r\nX-Sender: ikkanshi@...\r\nX-Apparently-To: nihontostudy@yahoogroups.com\r\nReceived: (qmail 83520 invoked from network); 23 Nov 2005 08:01:43 -0000\r\nReceived: from unknown (66.218.66.172)\n  by m32.grp.scd.yahoo.com with QMQP; 23 Nov 2005 08:01:43 -0000\r\nReceived: from unknown (HELO vscan02.westnet.com.au) (203.10.1.132)\n  by mta4.grp.scd.yahoo.com with SMTP; 23 Nov 2005 08:01:42 -0000\r\nReceived: from localhost (localhost.localdomain [127.0.0.1])\n\tby localhost (Postfix) with ESMTP id 88C2711B29B\n\tfor &lt;nihontostudy@yahoogroups.com&gt;; Wed, 23 Nov 2005 15:59:49 +0800 (WST)\r\nReceived: from vscan02.westnet.com.au ([127.0.0.1])\n by localhost (vscan02.westnet.com.au [127.0.0.1]) (amavisd-new, port 10024)\n with ESMTP id 06874-03 for &lt;nihontostudy@yahoogroups.com&gt;;\n Wed, 23 Nov 2005 15:59:49 +0800 (WST)\r\nReceived: from [192.168.0.3] (dsl-202-72-174-81.wa.westnet.com.au [202.72.174.81])\n\tby vscan02.westnet.com.au (Postfix) with ESMTP id 3EC2E11B2A9\n\tfor &lt;nihontostudy@yahoogroups.com&gt;; Wed, 23 Nov 2005 15:59:49 +0800 (WST)\r\nMessage-ID: &lt;4384217C.2060101@...&gt;\r\nDate: Wed, 23 Nov 2005 15:59:56 +0800\r\nUser-Agent: Mozilla Thunderbird 1.0.6 (Windows/20050716)\r\nX-Accept-Language: en-us, en\r\nMIME-Version: 1.0\r\nTo: nihontostudy@yahoogroups.com\r\nReferences: &lt;dllr7r+dbl4@...&gt;\r\nIn-Reply-To: &lt;dllr7r+dbl4@...&gt;\r\nX-eGroups-Msg-Info: 1:12:0:0\r\nFrom: Richard Turner &lt;ikkanshi@...&gt;\r\nReply-To: ikkanshi@...\r\nSubject: tsuba question\r\nX-Yahoo-Group-Post: member; u=122856650; y=VI6JoSu4_hZYtQejusb1EgQ1xqirlD_WG2EnHUkqx2wj\r\nX-Yahoo-Profile: retalt\r\nContent-Type: text/plain; charset=US-ASCII\r\nContent-Transfer-Encoding: 7bit\r\n\r\nhttp://www.nihonto-club.net/upload/joyimages/2440.jpg\n\nHello group, I have a small Ji Sukashi tsuba I think is Edo Owari \nschool. It has long running\ntokettsu in the mimi and looks well forged.\n\nMy question is in regards to the theme. I see to geese at 12 and 6 \noclock, what the the items at 2, 4, 8 and 1\n0 oclock, are they plant fonds ?.\n\nDo the two sections that come in from the mimi to the hitsu ana mean \nanything ?.\n\nThank you for your time.\n\ncheers\n\nRich Turner\n\n\n[Non-text portions of this message have been removed]\n\n\n"
}