{
    "userId": 122856650,
    "authorName": "Richard Turner",
    "from": "Richard Turner &lt;ikkanshi@...&gt;",
    "profile": "retalt",
    "replyTo": "LIST",
    "senderId": "duzuRJQawyx21nx8Ep6wxtM5an3G24mvZXeJ981XqmXixHj8oqgjpwcMMD4awC_QK3y5dmi0IXEZkhjWao798uOH7opp7FfHVzXQZW1rqA",
    "spamInfo": {
        "isSpam": false,
        "reason": "4"
    },
    "subject": "Re: [nihontostudy] Re: edo jidai Goto school secrets book..........",
    "postDate": "1133763858",
    "msgId": 3567,
    "canDelete": false,
    "contentTrasformed": false,
    "systemMessage": false,
    "headers": {
        "messageIdInHeader": "PDQzOTNERDEyLjgwOTAyMDVAd2VzdG5ldC5jb20uYXU+",
        "inReplyToHeader": "PGRuMGx1NiszOWJqQGVHcm91cHMuY29tPg==",
        "referencesHeader": "PGRuMGx1NiszOWJqQGVHcm91cHMuY29tPg=="
    },
    "prevInTopic": 3566,
    "nextInTopic": 3568,
    "prevInTime": 3566,
    "nextInTime": 3568,
    "topicId": 3562,
    "numMessagesInTopic": 11,
    "msgSnippet": "I will have a look tonight mate. Sorry, I have Wakayama ( 3 books ) and the the Kanzan Tosa Koza ( 6 books ), are they the ones you mean ?. rich Richard Turner",
    "rawEmail": "Return-Path: &lt;ikkanshi@...&gt;\r\nX-Sender: ikkanshi@...\r\nX-Apparently-To: nihontostudy@yahoogroups.com\r\nReceived: (qmail 27160 invoked from network); 5 Dec 2005 06:27:15 -0000\r\nReceived: from unknown (66.218.66.218)\n  by m32.grp.scd.yahoo.com with QMQP; 5 Dec 2005 06:27:15 -0000\r\nReceived: from unknown (HELO mail.amnet.net.au) (203.161.127.2)\n  by mta3.grp.scd.yahoo.com with SMTP; 5 Dec 2005 06:27:14 -0000\r\nReceived: (qmail 3944 invoked by uid 510); 5 Dec 2005 06:24:02 -0000\r\nReceived: from ikkanshi@... by willow.amnet.net.au by uid 502 with qmail-scanner-1.22-st-qms \n (clamdscan: 0.73. spamassassin: 2.55.  Clear:RC:1(203.161.69.91):. \n Processed in 1.88053 secs); 05 Dec 2005 06:24:02 -0000\r\nX-Antivirus-Amnet-Mail-From: ikkanshi@... via willow.amnet.net.au\r\nX-Antivirus-Amnet: 1.22-st-qms (Clear:RC:1(203.161.69.91):. Processed in 1.88053 secs Process 3922)\r\nReceived: from 203.161.69.91.dyn.amnet.net.au (HELO ?192.168.0.14?) (203.161.69.91)\n  by mail.amnet.net.au with SMTP; 5 Dec 2005 06:24:00 -0000\r\nMessage-ID: &lt;4393DD12.8090205@...&gt;\r\nDate: Mon, 05 Dec 2005 14:24:18 +0800\r\nUser-Agent: Mozilla Thunderbird 1.0 (Windows/20041206)\r\nX-Accept-Language: en-us, en\r\nMIME-Version: 1.0\r\nTo: nihontostudy@yahoogroups.com\r\nReferences: &lt;dn0lu6+39bj@...&gt;\r\nIn-Reply-To: &lt;dn0lu6+39bj@...&gt;\r\nX-eGroups-Msg-Info: 2:4:12:0\r\nFrom: Richard Turner &lt;ikkanshi@...&gt;\r\nReply-To: ikkanshi@...\r\nSubject: Re: [nihontostudy] Re: edo jidai Goto school secrets book..........\r\nX-Yahoo-Group-Post: member; u=122856650; y=ADPUwersuNt40dEXz0nBONc74EBVeG659ILbotWWlcgY\r\nX-Yahoo-Profile: retalt\r\nContent-Type: text/plain; charset=ISO-8859-1\r\nContent-Transfer-Encoding: quoted-printable\r\n\r\nI will have a look tonight mate. Sorry, I have Wakayama ( 3 books ) and \nth=\r\ne the Kanzan Tosa Koza ( 6 books ), are they the ones you mean ?.\n\nrich\n\nRi=\r\nchard Turner\nNihont=F4 Message Board\n&lt;http://www.nihontomessageboard.com/nm=\r\nb&gt;\n- /for the discussion and sharing of all things Nihont=F4/\n\n \n\n\n\nbungota=\r\nkadasword wrote:\n\n&gt;ye all,\n&gt;I checked Sato Kenzan ( spelling ? ) multi volu=\r\nmes on kodogu ( Trickie, \n&gt;you have that set of books )............. look a=\r\nt the Goto volume, page \n&gt;270 - 272.\n&gt;Looks familiar ? same book .\n&gt;So.....=\r\n...... if modan authority used this book as reference, I \n&gt;wouldn&#39;t call it=\r\n an novelty item.\n&gt;\n&gt;Milt\n&gt;\n&gt;\n&gt;\n&gt;\n&gt;\n&gt;\n&gt;\n&gt;\n&gt; \n&gt;Yahoo! Groups Links\n&gt;\n&gt;\n&gt;\n&gt; \n=\r\n&gt;\n&gt;\n&gt;\n&gt;  \n&gt;\n\n\n[Non-text portions of this message have been removed]\n\n\n"
}