{
    "userId": 27642611,
    "authorName": "Richard George",
    "from": "Richard George &lt;rkg@...&gt;",
    "profile": "rkgatteleport",
    "replyTo": "LIST",
    "senderId": "cFGKEYZaNkaBGXYjXFZOiBLDBE_QVUJ3tALSGvMT_JYVfJh0NnSz6fg-QL9Nhvk0dmkBhGOi4MfsH4eO9HmZgYvmbIE1dYAj",
    "spamInfo": {
        "isSpam": false,
        "reason": "0"
    },
    "subject": "Re: [nihontostudy] Mysterious Do-gooder",
    "postDate": "1172151343",
    "msgId": 4885,
    "canDelete": false,
    "contentTrasformed": false,
    "systemMessage": false,
    "headers": {
        "messageIdInHeader": "PDQ1REQ5QzJGLjQwMDA1MDhAdGVsZXBvcnQuY29tPg==",
        "referencesHeader": "PDAwMWYwMWM3NTY4NSRlOThhZGYyMCQ5ZjQxYThjMEBJTlNUSVRVVEU+"
    },
    "prevInTopic": 4884,
    "nextInTopic": 4886,
    "prevInTime": 4884,
    "nextInTime": 4886,
    "topicId": 4882,
    "numMessagesInTopic": 16,
    "msgSnippet": "Mark, yeah, except that the British authorities are probably looking for the guy so he can be arrested for weapons violations... rkg (Richard George)",
    "rawEmail": "Return-Path: &lt;rkg@...&gt;\r\nX-Sender: rkg@...\r\nX-Apparently-To: nihontostudy@yahoogroups.com\r\nReceived: (qmail 82991 invoked from network); 22 Feb 2007 13:42:42 -0000\r\nReceived: from unknown (66.218.67.36)\n  by m27.grp.scd.yahoo.com with QMQP; 22 Feb 2007 13:42:42 -0000\r\nReceived: from unknown (HELO elasmtp-curtail.atl.sa.earthlink.net) (209.86.89.64)\n  by mta10.grp.scd.yahoo.com with SMTP; 22 Feb 2007 13:42:42 -0000\r\nReceived: from [68.167.255.116] (helo=teleport.com)\n\tby elasmtp-curtail.atl.sa.earthlink.net with asmtp (Exim 4.34)\n\tid 1HKE6j-0004mw-KM\n\tfor nihontostudy@yahoogroups.com; Thu, 22 Feb 2007 08:35:38 -0500\r\nMessage-ID: &lt;45DD9C2F.4000508@...&gt;\r\nDate: Thu, 22 Feb 2007 05:35:43 -0800\r\nUser-Agent: Mozilla/5.0 (Windows; U; Windows NT 5.1; en-US; rv:1.0.2) Gecko/20021120 Netscape/7.01 (NSCD7.01)\r\nX-Accept-Language: en-us, en\r\nMIME-Version: 1.0\r\nTo: nihontostudy@yahoogroups.com\r\nReferences: &lt;001f01c75685$e98adf20$9f41a8c0@INSTITUTE&gt;\r\nContent-Type: text/plain; charset=us-ascii; format=flowed\r\nContent-Transfer-Encoding: 7bit\r\nX-ELNK-Trace: 301b3c924afacd2ce4c9bdbfb214d21cf0bbaa830a3891f47ffdfc62a2887daa350badd9bab72f9c350badd9bab72f9c350badd9bab72f9c350badd9bab72f9c\r\nX-eGroups-Msg-Info: 1:0:0:0\r\nFrom: Richard George &lt;rkg@...&gt;\r\nSubject: Re: [nihontostudy] Mysterious Do-gooder\r\nX-Yahoo-Group-Post: member; u=27642611; y=ZHOcDaetRSa8dLNxVJmUwUZKGWCbHELFbUyvZqK2Uy4-A3v6x6xmKg\r\nX-Yahoo-Profile: rkgatteleport\r\n\r\nMark,\n\nyeah, except that the British authorities are probably looking for the \nguy so he can be arrested for weapons violations...\n\nrkg\n(Richard George)\n\nMark Jaillet wrote:\n\n&gt;Finally,  I positive modern day story involving a sword.  How refreshing!\n&gt; \n&gt;Mark\n&gt; \n&gt; \n&gt;\n&gt;\n&gt;  \n&gt;\n\n\n\n"
}