{
    "userId": 70968620,
    "authorName": "John Berta",
    "from": "&quot;John Berta&quot; &lt;johnberta@...&gt;",
    "profile": "gaigin2000",
    "replyTo": "LIST",
    "senderId": "flXCQBcV5pRV5t6dpP0TkcILecAz6P3gDau1y_Tw7Y4aMdLzFkgkbRkf4NXY0qXsMBYHQd6oUnsbsY_iNMrz_UIDPpr3ztODBA",
    "spamInfo": {
        "isSpam": false,
        "reason": "12"
    },
    "subject": "Re: [nihontostudy] Tosogu for Sale",
    "postDate": "1219584766",
    "msgId": 5440,
    "canDelete": false,
    "contentTrasformed": false,
    "systemMessage": false,
    "headers": {
        "messageIdInHeader": "PDAwMWQwMWM5MDVlZCRlNTU0ODc4MCQxYzAyYThjMEBCYXNlPg==",
        "referencesHeader": "PGc4cmt1aStmaG9nQGVHcm91cHMuY29tPg=="
    },
    "prevInTopic": 5438,
    "nextInTopic": 0,
    "prevInTime": 5439,
    "nextInTime": 5441,
    "topicId": 5438,
    "numMessagesInTopic": 2,
    "msgSnippet": "Hi Richard; Your links do not work. John ... From: Richard Turner To: nihontostudy@yahoogroups.com Sent: Sunday, August 24, 2008 5:41 AM Subject:",
    "rawEmail": "Return-Path: &lt;johnberta@...&gt;\r\nX-Sender: johnberta@...\r\nX-Apparently-To: nihontostudy@yahoogroups.com\r\nX-Received: (qmail 75928 invoked from network); 24 Aug 2008 13:32:53 -0000\r\nX-Received: from unknown (66.218.67.97)\n  by m47.grp.scd.yahoo.com with QMQP; 24 Aug 2008 13:32:53 -0000\r\nX-Received: from unknown (HELO defout.telus.net) (199.185.220.240)\n  by mta18.grp.scd.yahoo.com with SMTP; 24 Aug 2008 13:32:53 -0000\r\nX-Received: from priv-edtnaa06.telusplanet.net ([154.20.87.169])\n          by priv-edtnes27.telusplanet.net\n          (InterMail vM.7.08.02.02 201-2186-121-104-20070414) with ESMTP\n          id &lt;20080824133324.KEPT11523.priv-edtnes27.telusplanet.net@...&gt;\n          for &lt;nihontostudy@yahoogroups.com&gt;;\n          Sun, 24 Aug 2008 07:33:24 -0600\r\nX-Received: from Base (d154-20-87-169.bchsia.telus.net [154.20.87.169])\n\tby priv-edtnaa06.telusplanet.net (BorderWare Security Platform) with SMTP id E62A0A30382B60E9\n\tfor &lt;nihontostudy@yahoogroups.com&gt;; Sun, 24 Aug 2008 07:32:51 -0600 (MDT)\r\nMessage-ID: &lt;001d01c905ed$e5548780$1c02a8c0@Base&gt;\r\nTo: &lt;nihontostudy@yahoogroups.com&gt;\r\nReferences: &lt;g8rkui+fhog@...&gt;\r\nDate: Sun, 24 Aug 2008 06:32:46 -0700\r\nMIME-Version: 1.0\r\nX-Priority: 3\r\nX-MSMail-Priority: Normal\r\nX-Mailer: Microsoft Outlook Express 6.00.2900.3138\r\nX-MimeOLE: Produced By Microsoft MimeOLE V6.00.2900.3350\r\nX-eGroups-Msg-Info: 1:12:0:0:0\r\nFrom: &quot;John Berta&quot; &lt;johnberta@...&gt;\r\nSubject: Re: [nihontostudy] Tosogu for Sale\r\nX-Yahoo-Group-Post: member; u=70968620; y=hyLkaI90-k1q7aOemxJt0DuJ6Zg2yIrp4Zyz0qp7FFJ9Qu5lwA\r\nX-Yahoo-Profile: gaigin2000\r\nContent-Type: text/plain; charset=US-ASCII\r\nContent-Transfer-Encoding: 7bit\r\n\r\nHi Richard;\n\nYour links do not work.\n\nJohn\n  ----- Original Message ----- \n  From: Richard Turner \n  To: nihontostudy@yahoogroups.com \n  Sent: Sunday, August 24, 2008 5:41 AM\n  Subject: [nihontostudy] Tosogu for Sale\n\n\n  Hi guys, for sale are several pieces from my collection. I am selling\n  these to help fund Japan 2008. All items boxed. These are some of the\n  better bits from my collection. It is time to upgrade though.\n\n  If you know anyone who may be interested, please pass this on.\n\n  All prices include shipping to members. More information from\n  ikkanshi@...\n\n  Richard Turner\n\n  http://www.nihontokanjipages.com/person . ppies.html\n  Solid Gold Ko Kinko Menuki - US$1500 Custom fitted box.\n\n  http://www.nihontokanjipages.com/person . enuki.html\n  Ko Kinko Menuki - NBTHK Hozon, custom fitted box. US$850.00\n\n  http://www.nihontokanjipages.com/person . shira.html\n  Ko Kinko Fuchigashira - Custom fitted box US$1000.00\n\n  http://www.nihontokanjipages.com/person . inter.html\n  Kyo Shoami tsuba - NBTHK Tokubetsu Keicho. US$600.00\n\n  http://www.nihontokanjipages.com/person . omaki.html\n  Momoyama period, Strong bones. US$650.00\n\n  http://www.nihontokanjipages.com/person . aneie.html\n  Kaneie Sukashi - USS1000.00\n\n  http://www.nihontokanjipages.com/person . rimon.html\n  Shoami sukashi - NBTHK Hozon, US$650.00\n\n  http://www.nihontokanjipages.com/person . hushi.html\n  Katchushi - Late Muromachi to Momoyama period. US$450.00\n\n  http://www.nihontokanjipages.com/person . iyoshi.htm\n  Tosa Myochin - Guarantee mei. US$750.00\n\n\n\n   \n\n[Non-text portions of this message have been removed]\n\n\n"
}